MANIFEST.in
README.md
setup.cfg
setup.py
src/phrasal/__init__.py
src/phrasal/__main__.py
src/phrasal/interfaces.py
src/phrasal/norm_punc.py
src/phrasal.egg-info/PKG-INFO
src/phrasal.egg-info/SOURCES.txt
src/phrasal.egg-info/dependency_links.txt
src/phrasal.egg-info/requires.txt
src/phrasal.egg-info/top_level.txt
src/phrasal.egg-info/zip-safe
src/phrasal/filterers/__init__.py
src/phrasal/filterers/pattern_sentence_filter.py
src/phrasal/filterers/pattern_sentence_filter.yaml
src/phrasal/html_converters/__init__.py
src/phrasal/html_converters/bs_converter.py
src/phrasal/html_converters/justext_converter.py
src/phrasal/links/__init__.py
src/phrasal/links/link_utils.py
src/phrasal/splitters/__init__.py
src/phrasal/splitters/mocy_splitter.py
src/phrasal/splitters/moses_splitter.py
src/phrasal/splitters/moses_splitter_prefixes.de.txt
src/phrasal/splitters/moses_splitter_prefixes.en.txt