Metadata-Version: 2.1
Name: phrasal
Version: 0.0.1
Summary: NLP tools to extract, normalize and filter sentences from text/HTML
Home-page: https://github.com/derlin/phrasal
Author: Lucy Linder
Author-email: lucy.derlin@gmail.com
License: Apache License 2.0
Platform: UNKNOWN
Classifier: Programming Language :: Python :: 3
Classifier: License :: OSI Approved :: Apache Software License
Classifier: Operating System :: OS Independent
Requires-Python: >=3.6
Provides-Extra: showcase
